fastai/__init__.py
fastai/_modidx.py
fastai/_nbdev.py
fastai/_pytorch_doc.py
fastai/basics.py
fastai/collab.py
fastai/distributed.py
fastai/fp16_utils.py
fastai/imports.py
fastai/interpret.py
fastai/layers.py
fastai/learner.py
fastai/losses.py
fastai/metrics.py
fastai/optimizer.py
fastai/test_utils.py
fastai/torch_basics.py
fastai/torch_core.py
fastai/torch_imports.py
fastai/callback/__init__.py
fastai/callback/all.py
fastai/callback/azureml.py
fastai/callback/captum.py
fastai/callback/channelslast.py
fastai/callback/comet.py
fastai/callback/core.py
fastai/callback/data.py
fastai/callback/fp16.py
fastai/callback/hook.py
fastai/callback/mixup.py
fastai/callback/preds.py
fastai/callback/progress.py
fastai/callback/rnn.py
fastai/callback/schedule.py
fastai/callback/tensorboard.py
fastai/callback/tracker.py
fastai/callback/training.py
fastai/callback/wandb.py
fastai/data/__init__.py
fastai/data/all.py
fastai/data/block.py
fastai/data/core.py
fastai/data/download_checks.py
fastai/data/external.py
fastai/data/load.py
fastai/data/transforms.py
fastai/medical/__init__.py
fastai/medical/imaging.py
fastai/medical/text.py
fastai/tabular/__init__.py
fastai/tabular/all.py
fastai/tabular/core.py
fastai/tabular/data.py
fastai/tabular/learner.py
fastai/tabular/model.py
fastai/text/__init__.py
fastai/text/all.py
fastai/text/core.py
fastai/text/data.py
fastai/text/learner.py
fastai/text/models/__init__.py
fastai/text/models/awdlstm.py
fastai/text/models/core.py
fastai/vision/__init__.py
fastai/vision/all.py
fastai/vision/augment.py
fastai/vision/core.py
fastai/vision/data.py
fastai/vision/gan.py
fastai/vision/learner.py
fastai/vision/utils.py
fastai/vision/widgets.py
fastai/vision/models/__init__.py
fastai/vision/models/all.py
fastai/vision/models/tvm.py
fastai/vision/models/unet.py
fastai/vision/models/xresnet.py
fastai-2.8.6.dist-info/licenses/LICENSE
fastai-2.8.6.dist-info/METADATA
fastai-2.8.6.dist-info/WHEEL
fastai-2.8.6.dist-info/entry_points.txt
fastai-2.8.6.dist-info/top_level.txt
fastai-2.8.6.dist-info/RECORD
