Metadata-Version: 2.4
Name: fastai
Version: 2.8.6
Summary: fastai simplifies training fast and accurate neural nets using modern best practices
Home-page: https://github.com/fastai/fastai
Author: Jeremy Howard, Sylvain Gugger, and contributors
Author-email: info@fast.ai
License: Apache Software License 2.0
Keywords: fastai,deep learning,machine learning
Classifier: Development Status :: 5 - Production/Stable
Classifier: Intended Audience :: Developers
Classifier: License :: OSI Approved :: Apache Software License
Classifier: Natural Language :: English
Classifier: Programming Language :: Python :: 3.10
Classifier: Programming Language :: Python :: 3.11
Classifier: Programming Language :: Python :: 3.12
Classifier: Programming Language :: Python :: 3.13
Requires-Python: >=3.10
License-File: LICENSE
Requires-Dist: pip
Requires-Dist: packaging
Requires-Dist: fastdownload<2,>=0.0.5
Requires-Dist: fastcore>=1.8.0
Requires-Dist: fasttransform>=0.0.2
Requires-Dist: torchvision>=0.11
Requires-Dist: matplotlib
Requires-Dist: pandas
Requires-Dist: requests
Requires-Dist: pyyaml
Requires-Dist: fastprogress>=0.2.4
Requires-Dist: pillow>=9.0.0
Requires-Dist: scikit-learn
Requires-Dist: scipy
Requires-Dist: spacy<4
Requires-Dist: packaging
Requires-Dist: plum-dispatch
Requires-Dist: cloudpickle
Requires-Dist: torch<2.10,>=1.10
Provides-Extra: dev
Requires-Dist: nbdev; extra == "dev"
Requires-Dist: ipywidgets; extra == "dev"
Requires-Dist: lightning; extra == "dev"
Requires-Dist: pytorch-ignite; extra == "dev"
Requires-Dist: transformers; extra == "dev"
Requires-Dist: sentencepiece; extra == "dev"
Requires-Dist: tensorboard; extra == "dev"
Requires-Dist: pydicom; extra == "dev"
Requires-Dist: catalyst; extra == "dev"
Requires-Dist: flask_compress; extra == "dev"
Requires-Dist: captum>=0.4.1; extra == "dev"
Requires-Dist: flask; extra == "dev"
Requires-Dist: wandb; extra == "dev"
Requires-Dist: kornia; extra == "dev"
Requires-Dist: scikit-image; extra == "dev"
Requires-Dist: comet_ml; extra == "dev"
Requires-Dist: albumentations; extra == "dev"
Requires-Dist: opencv-python; extra == "dev"
Requires-Dist: pyarrow; extra == "dev"
Requires-Dist: ninja; extra == "dev"
Requires-Dist: timm>=0.9; extra == "dev"
Requires-Dist: accelerate>=0.21; extra == "dev"
Requires-Dist: ipykernel; extra == "dev"
Dynamic: author
Dynamic: author-email
Dynamic: classifier
Dynamic: description
Dynamic: description-content-type
Dynamic: home-page
Dynamic: keywords
Dynamic: license
Dynamic: license-file
Dynamic: provides-extra
Dynamic: requires-dist
Dynamic: requires-python
Dynamic: summary
